MANIFEST.in
README.md
setup.cfg
setup.py
ipmininet/__init__.py
ipmininet/__main__.py
ipmininet/clean.py
ipmininet/cli.py
ipmininet/ipnet.py
ipmininet/ipswitch.py
ipmininet/iptopo.py
ipmininet/link.py
ipmininet/node_description.py
ipmininet/overlay.py
ipmininet/srv6.py
ipmininet/topologydb.py
ipmininet/utils.py
ipmininet.egg-info/PKG-INFO
ipmininet.egg-info/SOURCES.txt
ipmininet.egg-info/dependency_links.txt
ipmininet.egg-info/requires.txt
ipmininet.egg-info/top_level.txt
ipmininet/examples/__init__.py
ipmininet/examples/__main__.py
ipmininet/examples/bgp_decision_process.py
ipmininet/examples/bgp_full_config.py
ipmininet/examples/bgp_local_pref.py
ipmininet/examples/bgp_med.py
ipmininet/examples/bgp_policies_1.py
ipmininet/examples/bgp_policies_2.py
ipmininet/examples/bgp_policies_3.py
ipmininet/examples/bgp_policies_4.py
ipmininet/examples/bgp_policies_5.py
ipmininet/examples/bgp_policies_adjust.py
ipmininet/examples/bgp_rr.py
ipmininet/examples/dns_advanced_network.py
ipmininet/examples/dns_network.py
ipmininet/examples/exabgp_prefix_injector.py
ipmininet/examples/gre.py
ipmininet/examples/iptables.py
ipmininet/examples/link_failure.py
ipmininet/examples/partial_static_address_network.py
ipmininet/examples/ripng_network.py
ipmininet/examples/ripng_network_adjust.py
ipmininet/examples/router_adv_network.py
ipmininet/examples/simple_bgp_network.py
ipmininet/examples/simple_openr_network.py
ipmininet/examples/simple_ospf_network.py
ipmininet/examples/simple_ospfv3_network.py
ipmininet/examples/spanning_tree.py
ipmininet/examples/spanning_tree_adjust.py
ipmininet/examples/spanning_tree_bus.py
ipmininet/examples/spanning_tree_cost.py
ipmininet/examples/spanning_tree_full_mesh.py
ipmininet/examples/spanning_tree_hub.py
ipmininet/examples/spanning_tree_intermediate.py
ipmininet/examples/srv6.py
ipmininet/examples/sshd.py
ipmininet/examples/static_address_network.py
ipmininet/examples/static_routing.py
ipmininet/examples/static_routing_failure.py
ipmininet/examples/static_routing_network_basic.py
ipmininet/examples/static_routing_network_complex.py
ipmininet/examples/tc_advanced_network.py
ipmininet/examples/tc_network.py
