Metadata-Version: 1.1
Name: ipmininet
Version: 1.0
Summary: A mininet extension providing components to emulate IPnetworks running multiple protocols.
Home-page: https://github.com/cnp3/ipmininet
Author: Olivier Tilmans, Mathieu Jadin
Author-email: olivier.tilmans@uclouvain.be, mathieu.jadin@uclouvain.be
License: GPLv2
Keywords: networking OSPF IP BGP quagga mininet
Platform: UNKNOWN
Classifier: License :: OSI Approved :: GNU General Public License v2 (GPLv2)
Classifier: Programming Language :: Python
Classifier: Development Status :: 4 - Beta
Classifier: Intended Audience :: Developers
Classifier: Topic :: System :: Networking
Classifier: Programming Language :: Python :: 3
Classifier: Programming Language :: Python :: 3.6
Classifier: Programming Language :: Python :: 3.7
Classifier: Programming Language :: Python :: 3.8
Classifier: Programming Language :: Python :: 3.9
